fantail_package/__init__.py
fantail_package/script.py
fantail_package-0.1.dist-info/METADATA
fantail_package-0.1.dist-info/WHEEL
fantail_package-0.1.dist-info/entry_points.txt
fantail_package-0.1.dist-info/top_level.txt
fantail_package-0.1.dist-info/RECORD
